<?xml version="1.0" encoding="UTF-8" standalone="yes"?><imgdir name="9400423.img"><imgdir name="info"><int name="bodyAttack" value="1"/><int name="level" value="180"/><int name="maxHP" value="500000000"/><int name="maxMP" value="20000000"/><int name="speed" value="40"/><int name="PADamage" value="1500"/><int name="PDDamage" value="1999"/><int name="MADamage" value="1300"/><int name="MDDamage" value="1300"/><int name="acc" value="320"/><int name="eva" value="72"/><int name="exp" value="35000000"/><int name="hpRecovery" value="800"/><int name="mpRecovery" value="700"/><int name="undead" value="0"/><int name="pushed" value="15000"/><float name="fs" value="10.0"/><int name="summonType" value="1"/><int name="boss" value="1"/><int name="firstAttack" value="1"/><string name="elemAttr" value="I3H1"/><int name="hpTagColor" value="2"/><int name="hpTagBgcolor" value="5"/><imgdir name="skill"><imgdir name="0"><int name="skill" value="156"/><int name="action" value="1"/><int name="level" value="1"/><int name="effectAfter" value="1600"/></imgdir><imgdir name="1"><int name="skill" value="114"/><int name="action" value="1"/><int name="level" value="28"/><int name="effectAfter" value="1360"/></imgdir><imgdir name="2"><int name="skill" value="102"/><int name="action" value="1"/><int name="level" value="5"/><int name="effectAfter" value="1800"/></imgdir><imgdir name="3"><int name="skill" value="103"/><int name="action" value="1"/><int name="level" value="4"/><int name="effectAfter" value="1800"/></imgdir><imgdir name="4"><int name="skill" value="200"/><int name="action" value="1"/><int name="level" value="174"/><int name="effectAfter" value="1600"/></imgdir></imgdir><string name="link" value="9400593"/></imgdir></imgdir>