<?xml version="1.0" encoding="UTF-8" standalone="yes"?><imgdir name="9420525.img"><imgdir name="info"><int name="bodyAttack" value="1"/><int name="firstAttack" value="1"/><int name="level" value="30"/><int name="maxHP" value="20"/><int name="maxMP" value="0"/><int name="PADamage" value="18"/><int name="PDDamage" value="0"/><int name="MADamage" value="0"/><int name="MDDamage" value="0"/><int name="eva" value="999"/><int name="exp" value="33"/><int name="undead" value="1"/><int name="pushed" value="30"/><float name="fs" value="10.0"/><int name="summonType" value="1"/><int name="invincible" value="1"/><int name="hideName" value="1"/><int name="noFlip" value="1"/></imgdir><imgdir name="stand"><canvas name="0" width="37" height="43"><vector name="origin" x="24" y="42"/><vector name="head" x="0" y="-42"/><int name="delay" value="300"/></canvas><canvas name="1" width="37" height="43"><vector name="origin" x="24" y="42"/><vector name="head" x="0" y="-42"/><int name="delay" value="300"/></canvas><canvas name="2" width="37" height="43"><vector name="origin" x="24" y="42"/><vector name="lt" x="-24" y="-42"/><int name="delay" value="300"/></canvas></imgdir><imgdir name="attack1"><imgdir name="info"><imgdir name="range"><vector name="lt" x="-128" y="-82"/><vector name="rb" x="32" y="0"/></imgdir><imgdir name="hit"><canvas name="0" width="104" height="139"><vector name="origin" x="53" y="121"/><vector name="lt" x="-47" y="-103"/><vector name="rb" x="40" y="8"/><vector name="head" x="7" y="-59"/><int name="delay" value="120"/></canvas><canvas name="1" width="108" height="151"><vector name="origin" x="52" y="133"/><vector name="lt" x="-50" y="-127"/><vector name="rb" x="54" y="9"/><vector name="head" x="1" y="-75"/><int name="delay" value="120"/></canvas><canvas name="2" width="119" height="156"><vector name="origin" x="62" y="138"/><vector name="lt" x="-59" y="-133"/><vector name="rb" x="53" y="16"/><vector name="head" x="8" y="-45"/><int name="delay" value="120"/></canvas><canvas name="3" width="118" height="140"><vector name="origin" x="58" y="123"/><vector name="lt" x="-52" y="-123"/><vector name="rb" x="60" y="11"/><vector name="head" x="7" y="-50"/><int name="delay" value="120"/></canvas><canvas name="4" width="112" height="137"><vector name="origin" x="55" y="126"/><vector name="lt" x="-54" y="-127"/><vector name="rb" x="55" y="6"/><vector name="head" x="4" y="-79"/><int name="delay" value="120"/></canvas><canvas name="5" width="96" height="135"><vector name="origin" x="41" y="127"/><vector name="lt" x="-40" y="-128"/><vector name="rb" x="55" y="6"/><vector name="head" x="8" y="-81"/><int name="delay" value="120"/></canvas><canvas name="6" width="62" height="111"><vector name="origin" x="31" y="130"/><vector name="lt" x="-31" y="-132"/><vector name="rb" x="31" y="-18"/><vector name="head" x="8" y="-59"/><int name="delay" value="120"/></canvas><int name="attach" value="1"/></imgdir><int name="type" value="0"/><int name="attackAfter" value="360"/><int name="effectAfter" value="1040"/></imgdir><canvas name="0" width="37" height="64"><vector name="origin" x="24" y="63"/><vector name="head" x="0" y="-64"/><int name="delay" value="120"/></canvas><canvas name="1" width="45" height="68"><vector name="origin" x="32" y="67"/><vector name="head" x="0" y="-64"/><int name="delay" value="120"/></canvas><canvas name="2" width="55" height="77"><vector name="origin" x="42" y="76"/><vector name="head" x="0" y="-64"/><int name="delay" value="120"/></canvas><canvas name="3" width="81" height="106"><vector name="origin" x="68" y="105"/><vector name="head" x="0" y="-64"/><int name="delay" value="120"/></canvas><canvas name="4" width="84" height="102"><vector name="origin" x="71" y="101"/><vector name="head" x="0" y="-64"/><int name="delay" value="120"/></canvas><canvas name="5" width="87" height="104"><vector name="origin" x="74" y="103"/><vector name="head" x="0" y="-64"/><int name="delay" value="120"/></canvas><canvas name="6" width="85" height="103"><vector name="origin" x="72" y="102"/><vector name="head" x="0" y="-64"/><int name="delay" value="120"/></canvas><canvas name="7" width="84" height="114"><vector name="origin" x="71" y="113"/><vector name="head" x="0" y="-64"/><int name="delay" value="120"/></canvas><canvas name="8" width="77" height="105"><vector name="origin" x="64" y="104"/><vector name="head" x="0" y="-64"/><int name="delay" value="120"/></canvas></imgdir><imgdir name="hit1"><canvas name="0" width="37" height="43"><vector name="origin" x="24" y="42"/><vector name="head" x="0" y="-42"/><int name="delay" value="300"/></canvas></imgdir><imgdir name="die1"><canvas name="0" width="37" height="43"><vector name="origin" x="24" y="42"/><vector name="head" x="0" y="-42"/><int name="delay" value="300"/></canvas></imgdir></imgdir>