<?xml version="1.0" encoding="UTF-8" standalone="yes"?><imgdir name="9270044.img"><imgdir name="info"><imgdir name="speak"><string name="0" value="n0"/><string name="1" value="n1"/></imgdir><canvas name="default" width="73" height="82"><vector name="origin" x="35" y="81"/></canvas></imgdir><imgdir name="stand"><canvas name="0" width="189" height="131"><vector name="origin" x="36" y="128"/></canvas><canvas name="1" width="189" height="130"><vector name="origin" x="36" y="127"/></canvas><canvas name="2" width="189" height="131"><vector name="origin" x="36" y="128"/></canvas><canvas name="3" width="189" height="130"><vector name="origin" x="36" y="127"/></canvas><canvas name="4" width="189" height="131"><vector name="origin" x="36" y="128"/></canvas><canvas name="5" width="189" height="130"><vector name="origin" x="36" y="127"/></canvas><canvas name="6" width="189" height="131"><vector name="origin" x="36" y="128"/></canvas><canvas name="7" width="189" height="130"><vector name="origin" x="36" y="127"/></canvas></imgdir><imgdir name="say"><canvas name="0" width="189" height="137"><vector name="origin" x="36" y="134"/></canvas><canvas name="1" width="189" height="139"><vector name="origin" x="36" y="136"/></canvas><canvas name="2" width="189" height="140"><vector name="origin" x="36" y="137"/></canvas><canvas name="3" width="189" height="141"><vector name="origin" x="36" y="138"/></canvas><canvas name="4" width="189" height="137"><vector name="origin" x="36" y="134"/></canvas><canvas name="5" width="189" height="139"><vector name="origin" x="36" y="136"/></canvas><canvas name="6" width="189" height="140"><vector name="origin" x="36" y="137"/></canvas><canvas name="7" width="189" height="141"><vector name="origin" x="36" y="138"/></canvas></imgdir><imgdir name="act"><canvas name="0" width="189" height="131"><vector name="origin" x="36" y="128"/></canvas><canvas name="1" width="188" height="130"><vector name="origin" x="35" y="127"/></canvas><canvas name="2" width="187" height="130"><vector name="origin" x="34" y="128"/></canvas><canvas name="3" width="186" height="129"><vector name="origin" x="33" y="127"/></canvas><canvas name="4" width="186" height="130"><vector name="origin" x="33" y="128"/></canvas><canvas name="5" width="187" height="129"><vector name="origin" x="34" y="127"/></canvas><canvas name="6" width="187" height="130"><vector name="origin" x="34" y="128"/></canvas><canvas name="7" width="187" height="129"><vector name="origin" x="34" y="127"/></canvas><canvas name="8" width="187" height="130"><vector name="origin" x="34" y="128"/></canvas><canvas name="9" width="188" height="130"><vector name="origin" x="35" y="127"/></canvas></imgdir></imgdir>